tests/__init__.py
tests/performance_setup.py
tests/test_check_elements.py
tests/test_cli.py
tests/test_click_create.py
tests/test_create_elements.py
tests/test_file_traverser.py
tests/test_list_elements.py
tests/test_performance.py
tests/test_process_elements.py
tests/test_process_elements_api.py
treqs/__init__.py
treqs/_version.py
treqs/check_elements.py
treqs/create_elements.py
treqs/extension_loader.py
treqs/external_id_utils.py
treqs/file_traverser.py
treqs/list_elements.py
treqs/main.py
treqs/process_elements.py
treqs/treqs_element.py
treqs_ng-1.6.5.dist-info/licenses/LICENSE
treqs_ng-1.6.5.dist-info/METADATA
treqs_ng-1.6.5.dist-info/WHEEL
treqs_ng-1.6.5.dist-info/entry_points.txt
treqs_ng-1.6.5.dist-info/top_level.txt
treqs_ng-1.6.5.dist-info/RECORD
