Metadata-Version: 2.4
Name: treqs-ng
Version: 1.6.5
Summary: Lightweight Git-native tool for managing requirements in agile projects.
Home-page: https://gitlab.com/treqs-on-git/treqs-ng
Author: Eric Knauss
Author-email: eric.knauss@cse.gu.se
Classifier: Development Status :: 5 - Production/Stable
Classifier: Intended Audience :: Developers
Classifier: Topic :: Software Development :: Documentation
Classifier: License :: OSI Approved :: MIT License
Classifier: Programming Language :: Python :: 3
Classifier: Programming Language :: Python :: 3.9
Classifier: Programming Language :: Python :: 3.10
Classifier: Programming Language :: Python :: 3.11
Classifier: Programming Language :: Python :: 3.12
Classifier: Programming Language :: Python :: 3.13
Requires-Python: >=3.9
License-File: LICENSE
Requires-Dist: click>=8.0
Requires-Dist: lxml>=4.9.3
Requires-Dist: pyyaml>=6.0
Provides-Extra: dev
Requires-Dist: coverage; extra == "dev"
Requires-Dist: coverage-badge; extra == "dev"
Requires-Dist: ruff; extra == "dev"
Dynamic: author
Dynamic: author-email
Dynamic: classifier
Dynamic: description
Dynamic: description-content-type
Dynamic: home-page
Dynamic: license-file
Dynamic: provides-extra
Dynamic: requires-dist
Dynamic: requires-python
Dynamic: summary
